pioton/__init__.py
pioton/pioton.py
pioton-0.3.9.data/scripts/tiomsaitheoir
pioton-0.3.9.dist-info/LICENCE.txt
pioton-0.3.9.dist-info/METADATA
pioton-0.3.9.dist-info/WHEEL
pioton-0.3.9.dist-info/top_level.txt
pioton-0.3.9.dist-info/RECORD
