Metadata-Version: 2.1
Name: pioton
Version: 0.3.9
Summary: píotón language is a superset of Python allowing it to be written in Irish. Not for use in any important work
Home-page: https://github.com/LukeRoantree4815162342/pioton
Download-URL: https://github.com/LukeRoantree4815162342/pioton/archive/v_030.tar.gz
Author: Luke Roantree
Author-email: luke@roantree.com
License: GPL
Keywords: IPython,Gaeilge,Irish
Platform: UNKNOWN
Classifier: Development Status :: 3 - Alpha
Classifier: Intended Audience :: Developers
Classifier: Topic :: Software Development :: Build Tools
Classifier: License :: OSI Approved :: GNU General Public License (GPL)
Classifier: Programming Language :: Python :: 3
Classifier: Programming Language :: Python :: 3.4
Classifier: Programming Language :: Python :: 3.5
Classifier: Programming Language :: Python :: 3.6
Classifier: Programming Language :: Python :: 3.7
Classifier: Programming Language :: Python :: 3.8
Classifier: Programming Language :: Python :: 3.9
License-File: LICENCE.txt
Requires-Dist: ipython
